jupyterlite_xeus_lua/__init__.py
jupyterlite_xeus_lua/_version.py
jupyterlite_xeus_lua/labextension/package.json
jupyterlite_xeus_lua/labextension/static/213.3e05e8eb821d9cb5ea3e.js
jupyterlite_xeus_lua/labextension/static/47.a20499c9f2d3eee4f3bf.js
jupyterlite_xeus_lua/labextension/static/534.913dbaac4c3a715cf84f.js
jupyterlite_xeus_lua/labextension/static/ef04946322537d832f3fad9e57f58276.png
jupyterlite_xeus_lua/labextension/static/f64815cfa6dda2af6b3518688380f849.png
jupyterlite_xeus_lua/labextension/static/remoteEntry.e78d78c300edd8e07311.js
jupyterlite_xeus_lua/labextension/static/style.js
jupyterlite_xeus_lua/labextension/static/third-party-licenses.json
jupyterlite_xeus_lua/labextension/static/xeus_kernel.wasm
jupyterlite_xeus_lua-0.3.3.data/data/share/jupyter/labextensions/jupyterlite-xeus-lua/install.json
jupyterlite_xeus_lua-0.3.3.data/data/share/jupyter/labextensions/jupyterlite-xeus-lua/package.json
jupyterlite_xeus_lua-0.3.3.data/data/share/jupyter/labextensions/jupyterlite-xeus-lua/static/213.3e05e8eb821d9cb5ea3e.js
jupyterlite_xeus_lua-0.3.3.data/data/share/jupyter/labextensions/jupyterlite-xeus-lua/static/47.a20499c9f2d3eee4f3bf.js
jupyterlite_xeus_lua-0.3.3.data/data/share/jupyter/labextensions/jupyterlite-xeus-lua/static/534.913dbaac4c3a715cf84f.js
jupyterlite_xeus_lua-0.3.3.data/data/share/jupyter/labextensions/jupyterlite-xeus-lua/static/ef04946322537d832f3fad9e57f58276.png
jupyterlite_xeus_lua-0.3.3.data/data/share/jupyter/labextensions/jupyterlite-xeus-lua/static/f64815cfa6dda2af6b3518688380f849.png
jupyterlite_xeus_lua-0.3.3.data/data/share/jupyter/labextensions/jupyterlite-xeus-lua/static/remoteEntry.e78d78c300edd8e07311.js
jupyterlite_xeus_lua-0.3.3.data/data/share/jupyter/labextensions/jupyterlite-xeus-lua/static/style.js
jupyterlite_xeus_lua-0.3.3.data/data/share/jupyter/labextensions/jupyterlite-xeus-lua/static/third-party-licenses.json
jupyterlite_xeus_lua-0.3.3.dist-info/LICENSE
jupyterlite_xeus_lua-0.3.3.dist-info/METADATA
jupyterlite_xeus_lua-0.3.3.dist-info/WHEEL
jupyterlite_xeus_lua-0.3.3.dist-info/top_level.txt
jupyterlite_xeus_lua-0.3.3.dist-info/RECORD
